Metadata-Version: 2.1
Name: xinabox-CW01-CW02-CORE
Version: 0.0.1
Summary: I2C Core
Home-page: https://github.com/xinabox/Python-CORE-CW01-CW02
Author: Luqmaan Baboo
Author-email: luqmaanbaboo@gmail.com
License: UNKNOWN
Platform: UNKNOWN
Classifier: Programming Language :: Python :: 3
Classifier: License :: OSI Approved :: MIT License
Classifier: Operating System :: OS Independent
Requires-Python: >=3.6
